MANIFEST.in
setup.py
bin/__init__.py
bin/hikvision-client-gtk
bin/hikvision-client-tk
hikvision_client/__init__.py
hikvision_client/main.py
hikvision_client/metadata.py
hikvision_client.egg-info/PKG-INFO
hikvision_client.egg-info/SOURCES.txt
hikvision_client.egg-info/dependency_links.txt
hikvision_client.egg-info/not-zip-safe
hikvision_client.egg-info/requires.txt
hikvision_client.egg-info/top_level.txt
hikvision_client/config/ConfigParser.py
hikvision_client/config/__init__.py
hikvision_client/resources/__init__.py
hikvision_client/tests/__init__.py
hikvision_client/userinterface/LoginGui.py
hikvision_client/userinterface/MainGui.py
hikvision_client/userinterface/__init__.py