Metadata-Version: 1.1
Name: hikvision-client
Version: 0.5
Summary: A graphical client software for Hikvision (and other RTSP-enabled) IP cameras
Home-page: http://namibsun.net/namboy94/hikvision-client
Author: Hermann Krumrey
Author-email: hermann@krumreyh.com
License: GNU GPL3
Platform: UNKNOWN
Classifier: Development Status :: 3 - Alpha
Classifier: License :: OSI Approved :: GNU General Public License v3 (GPLv3)
Classifier: Intended Audience :: End Users/Desktop
Classifier: Programming Language :: Python :: 3
Classifier: Topic :: Multimedia :: Video :: Display
Classifier: Natural Language :: English
Classifier: Operating System :: OS Independent
Classifier: Environment :: Other Environment
Requires: VLC
